CHANGES
LICENSE
MANIFEST.in
README
ez_setup.py
setup.py
TracSubPages/__init__.py
TracSubPages/macro.py
TracSubPages.egg-info/PKG-INFO
TracSubPages.egg-info/SOURCES.txt
TracSubPages.egg-info/dependency_links.txt
TracSubPages.egg-info/entry_points.txt
TracSubPages.egg-info/top_level.txt