Metadata-Version: 1.0
Name: TracSubPages
Version: 0.5
Summary: A Trac macro that displays the bodies of wiki pages inside other wiki pages
Home-page: http://github.com/jetheis/TracSubPages
Author: Jimmy Theis
Author-email: jimmy@jetheis.com
License: GPLv3
Platform: UNKNOWN
